foliant/backends/confluence/__init__.py
foliant/backends/confluence/confluence.py
foliant/backends/confluence/constants.py
foliant/backends/confluence/convert.py
foliant/backends/confluence/extracter.py
foliant/backends/confluence/ref_diff.py
foliant/backends/confluence/uploader.py
foliant/backends/confluence/wrapper.py
foliant/preprocessors/confluence.py
foliant/preprocessors/confluence_final/__init__.py
foliant/preprocessors/confluence_final/confluence_final.py
foliant/preprocessors/confluence_final/process.py
foliantcontrib_confluence-0.6.22.dist-info/licenses/LICENSE
foliantcontrib_confluence-0.6.22.dist-info/METADATA
foliantcontrib_confluence-0.6.22.dist-info/WHEEL
foliantcontrib_confluence-0.6.22.dist-info/top_level.txt
foliantcontrib_confluence-0.6.22.dist-info/RECORD
