Metadata-Version: 2.4
Name: foliantcontrib.confluence
Version: 0.6.22
Summary: Confluence backend for Foliant documentation generator.
Home-page: https://github.com/foliant-docs/foliantcontrib.confluence
Author: Daniil Minukhin
Author-email: ddddsa@gmail.com
License: MIT
Platform: any
Classifier: Development Status :: 5 - Production/Stable
Classifier: Environment :: Console
Classifier: Intended Audience :: Developers
Classifier: License :: OSI Approved :: MIT License
Classifier: Operating System :: OS Independent
Classifier: Programming Language :: Python
Classifier: Topic :: Documentation
Classifier: Topic :: Utilities
License-File: LICENSE
Requires-Dist: foliant>=1.0.8
Requires-Dist: atlassian-python-api==4.0.5
Requires-Dist: foliantcontrib.utils>=1.0.2
Requires-Dist: foliantcontrib.flatten>=1.0.5
Requires-Dist: foliantcontrib.meta>=1.3.1
Requires-Dist: pyparsing
Requires-Dist: beautifulsoup4
Dynamic: author
Dynamic: author-email
Dynamic: classifier
Dynamic: description
Dynamic: description-content-type
Dynamic: home-page
Dynamic: license
Dynamic: license-file
Dynamic: platform
Dynamic: requires-dist
Dynamic: summary
